ossx/__init__.py
ossx/_http.py
ossx/bucket.py
ossx/iterators.py
ossx/models.py
ossx/patch.py
ossx/select_response.py
ossx/utils.py
ossx-2.19.1.post1.dist-info/METADATA
ossx-2.19.1.post1.dist-info/WHEEL
ossx-2.19.1.post1.dist-info/RECORD
