Metadata-Version: 2.3
Name: ossx
Version: 2.19.1.post1
Summary: aliyun oss sdk for python async
Author: sswest
Requires-Python: >=3.8,<4.0
Classifier: Programming Language :: Python :: 3
Classifier: Programming Language :: Python :: 3.8
Classifier: Programming Language :: Python :: 3.9
Classifier: Programming Language :: Python :: 3.10
Classifier: Programming Language :: Python :: 3.11
Classifier: Programming Language :: Python :: 3.12
Classifier: Programming Language :: Python :: 3.13
Requires-Dist: aiofiles (>=0.7.0)
Requires-Dist: httpx (>=0.23,<1.0)
Requires-Dist: oss2 (>=2.18,<3.0)
